deserve.py
deserve-0.2.dist-info/LICENSE
deserve-0.2.dist-info/WHEEL
deserve-0.2.dist-info/METADATA
deserve-0.2.dist-info/RECORD
