Metadata-Version: 2.1
Name: deserve
Version: 0.2
Summary: Deserve is a nanoframework for serving ML models
Author-email: Matías Battocchia <battox@gmail.com>
Project-URL: Home, https://github.com/matiasbattocchia/deserve
